abcXYZ/__init__.py
abcXYZ-0.1.dist-info/LICENCE.txt
abcXYZ-0.1.dist-info/METADATA
abcXYZ-0.1.dist-info/WHEEL
abcXYZ-0.1.dist-info/top_level.txt
abcXYZ-0.1.dist-info/RECORD
