Metadata-Version: 2.1
Name: abcXYZ
Version: 0.1
Summary: Model created for education
Home-page: UNKNOWN
Author: Jupiter
Author-email: npsjupiter@gmail.com
License: UNKNOWN
Platform: UNKNOWN
Classifier: Programming Language :: Python :: 3
Classifier: License :: OSI Approved :: MIT License
Classifier: Operating System :: OS Independent
License-File: LICENCE.txt
